{
  "lastUpdated": "2026-03-30T18:31:03.644691Z",
  "counties": [
    {
      "name": "Dinwiddie",
      "temp": 69,
      "rh": 44,
      "dewPoint": 47,
      "wind": 11,
      "gust": 21,
      "dangerClass": 3
    },
    {
      "name": "Brunswick",
      "temp": 71,
      "rh": 48,
      "dewPoint": 50,
      "wind": 17,
      "gust": 25,
      "dangerClass": 3
    },
    {
      "name": "Greensville",
      "temp": 71,
      "rh": 45,
      "dewPoint": 48,
      "wind": 11,
      "gust": 21,
      "dangerClass": 3
    },
    {
      "name": "Amelia",
      "temp": 68,
      "rh": 65,
      "dewPoint": 56,
      "wind": 7,
      "gust": 9,
      "dangerClass": 1
    },
    {
      "name": "Prince George",
      "temp": 69,
      "rh": 44,
      "dewPoint": 47,
      "wind": 11,
      "gust": 21,
      "dangerClass": 3
    },
    {
      "name": "Nottoway",
      "temp": 68,
      "rh": 65,
      "dewPoint": 56,
      "wind": 7,
      "gust": 9,
      "dangerClass": 1
    }
  ],
  "alerts": [
    "Dinwiddie: High gusts (21 mph)",
    "Brunswick: High gusts (25 mph)",
    "Greensville: High gusts (21 mph)",
    "Prince George: High gusts (21 mph)"
  ]
}