{
  "lastUpdated": "2025-12-04T06:28:10.256075Z",
  "counties": [
    {
      "name": "Brunswick",
      "temp": 30,
      "rh": 99,
      "dewPoint": 30,
      "wind": 0,
      "gust": 0,
      "dangerClass": 1
    },
    {
      "name": "Greensville",
      "temp": 25,
      "rh": 93,
      "dewPoint": 23,
      "wind": 0,
      "gust": 0,
      "dangerClass": 1
    },
    {
      "name": "Amelia",
      "temp": 28,
      "rh": 99,
      "dewPoint": 28,
      "wind": 0,
      "gust": 0,
      "dangerClass": 1
    },
    {
      "name": "Prince George",
      "temp": null,
      "rh": null,
      "dewPoint": null,
      "wind": 0,
      "gust": 0,
      "dangerClass": 2
    },
    {
      "name": "Nottoway",
      "temp": 28,
      "rh": 99,
      "dewPoint": 28,
      "wind": 0,
      "gust": 0,
      "dangerClass": 1
    }
  ],
  "alerts": []
}