{
  "lastUpdated": "2026-06-30T18:49:14.821875Z",
  "counties": [
    {
      "name": "Dinwiddie",
      "temp": 85,
      "rh": 42,
      "dewPoint": 60,
      "wind": 0,
      "gust": 0,
      "dangerClass": 2
    },
    {
      "name": "Brunswick",
      "temp": 89,
      "rh": 43,
      "dewPoint": 63,
      "wind": 6,
      "gust": 8,
      "dangerClass": 2
    },
    {
      "name": "Greensville",
      "temp": 86,
      "rh": 50,
      "dewPoint": 65,
      "wind": 7,
      "gust": 9,
      "dangerClass": 2
    },
    {
      "name": "Amelia",
      "temp": 89,
      "rh": 52,
      "dewPoint": 69,
      "wind": 5,
      "gust": 6,
      "dangerClass": 2
    },
    {
      "name": "Prince George",
      "temp": 85,
      "rh": 42,
      "dewPoint": 60,
      "wind": 0,
      "gust": 0,
      "dangerClass": 2
    },
    {
      "name": "Nottoway",
      "temp": 89,
      "rh": 52,
      "dewPoint": 69,
      "wind": 5,
      "gust": 6,
      "dangerClass": 2
    }
  ],
  "alerts": []
}