{
  "lastUpdated": "2025-12-23T18:44:26.059944Z",
  "counties": [
    {
      "name": "Dinwiddie",
      "temp": 57,
      "rh": 42,
      "dewPoint": 34,
      "wind": 11,
      "gust": 15,
      "dangerClass": 2
    },
    {
      "name": "Brunswick",
      "temp": 59,
      "rh": 40,
      "dewPoint": 35,
      "wind": 9,
      "gust": 12,
      "dangerClass": 2
    },
    {
      "name": "Greensville",
      "temp": 55,
      "rh": 49,
      "dewPoint": 36,
      "wind": 9,
      "gust": 16,
      "dangerClass": 2
    },
    {
      "name": "Amelia",
      "temp": 56,
      "rh": 54,
      "dewPoint": 40,
      "wind": 7,
      "gust": 9,
      "dangerClass": 1
    },
    {
      "name": "Prince George",
      "temp": 57,
      "rh": 42,
      "dewPoint": 34,
      "wind": 11,
      "gust": 15,
      "dangerClass": 2
    },
    {
      "name": "Nottoway",
      "temp": 56,
      "rh": 54,
      "dewPoint": 40,
      "wind": 7,
      "gust": 9,
      "dangerClass": 1
    }
  ],
  "alerts": []
}