{
  "lastUpdated": "2026-04-16T18:25:40.615652Z",
  "counties": [
    {
      "name": "Dinwiddie",
      "temp": 89,
      "rh": null,
      "dewPoint": null,
      "wind": 0,
      "gust": 0,
      "dangerClass": 2
    },
    {
      "name": "Brunswick",
      "temp": null,
      "rh": null,
      "dewPoint": null,
      "wind": null,
      "gust": null,
      "dangerClass": 1
    },
    {
      "name": "Greensville",
      "temp": 87,
      "rh": 37,
      "dewPoint": 57,
      "wind": 11,
      "gust": 18,
      "dangerClass": 4
    },
    {
      "name": "Amelia",
      "temp": 90,
      "rh": 37,
      "dewPoint": 60,
      "wind": 7,
      "gust": 9,
      "dangerClass": 3
    },
    {
      "name": "Prince George",
      "temp": 89,
      "rh": null,
      "dewPoint": null,
      "wind": 0,
      "gust": 0,
      "dangerClass": 2
    },
    {
      "name": "Nottoway",
      "temp": 90,
      "rh": 37,
      "dewPoint": 60,
      "wind": 7,
      "gust": 9,
      "dangerClass": 3
    }
  ],
  "alerts": []
}