{
  "lastUpdated": "2026-02-21T18:27:50.761337Z",
  "counties": [
    {
      "name": "Dinwiddie",
      "temp": 56,
      "rh": null,
      "dewPoint": null,
      "wind": 3,
      "gust": 4,
      "dangerClass": 2
    },
    {
      "name": "Brunswick",
      "temp": 56,
      "rh": 49,
      "dewPoint": 37,
      "wind": 8,
      "gust": 10,
      "dangerClass": 1
    },
    {
      "name": "Greensville",
      "temp": 57,
      "rh": 40,
      "dewPoint": 33,
      "wind": 0,
      "gust": 0,
      "dangerClass": 1
    },
    {
      "name": "Amelia",
      "temp": 60,
      "rh": 38,
      "dewPoint": 34,
      "wind": 6,
      "gust": 8,
      "dangerClass": 1
    },
    {
      "name": "Prince George",
      "temp": 56,
      "rh": null,
      "dewPoint": null,
      "wind": 3,
      "gust": 4,
      "dangerClass": 2
    },
    {
      "name": "Nottoway",
      "temp": 60,
      "rh": 38,
      "dewPoint": 34,
      "wind": 6,
      "gust": 8,
      "dangerClass": 1
    }
  ],
  "alerts": []
}