{
  "lastUpdated": "2026-04-16T12:37:36.347438Z",
  "counties": [
    {
      "name": "Dinwiddie",
      "temp": 67,
      "rh": 67,
      "dewPoint": 56,
      "wind": 3,
      "gust": 4,
      "dangerClass": 1
    },
    {
      "name": "Brunswick",
      "temp": 65,
      "rh": 80,
      "dewPoint": 59,
      "wind": 9,
      "gust": 12,
      "dangerClass": 2
    },
    {
      "name": "Greensville",
      "temp": 65,
      "rh": 81,
      "dewPoint": 59,
      "wind": 6,
      "gust": 8,
      "dangerClass": 1
    },
    {
      "name": "Amelia",
      "temp": 68,
      "rh": 71,
      "dewPoint": 58,
      "wind": 5,
      "gust": 6,
      "dangerClass": 1
    },
    {
      "name": "Prince George",
      "temp": 67,
      "rh": 67,
      "dewPoint": 56,
      "wind": 3,
      "gust": 4,
      "dangerClass": 1
    },
    {
      "name": "Nottoway",
      "temp": 68,
      "rh": 71,
      "dewPoint": 58,
      "wind": 5,
      "gust": 6,
      "dangerClass": 1
    }
  ],
  "alerts": []
}