{
  "lastUpdated": "2026-07-02T00:40:11.929000Z",
  "counties": [
    {
      "name": "Dinwiddie",
      "temp": 86,
      "rh": 65,
      "dewPoint": 73,
      "wind": 0,
      "gust": 0,
      "dangerClass": 2
    },
    {
      "name": "Brunswick",
      "temp": 89,
      "rh": 63,
      "dewPoint": 75,
      "wind": 5,
      "gust": 6,
      "dangerClass": 2
    },
    {
      "name": "Greensville",
      "temp": 86,
      "rh": 64,
      "dewPoint": 72,
      "wind": 5,
      "gust": 6,
      "dangerClass": 2
    },
    {
      "name": "Amelia",
      "temp": 92,
      "rh": 65,
      "dewPoint": 79,
      "wind": 0,
      "gust": 0,
      "dangerClass": 2
    },
    {
      "name": "Prince George",
      "temp": 86,
      "rh": 65,
      "dewPoint": 73,
      "wind": 0,
      "gust": 0,
      "dangerClass": 2
    },
    {
      "name": "Nottoway",
      "temp": 92,
      "rh": 65,
      "dewPoint": 79,
      "wind": 0,
      "gust": 0,
      "dangerClass": 2
    }
  ],
  "alerts": []
}