{
  "lastUpdated": "2026-02-01T03:25:25.539063Z",
  "counties": [
    {
      "name": "Dinwiddie",
      "temp": 21,
      "rh": 52,
      "dewPoint": 6,
      "wind": 11,
      "gust": 26,
      "dangerClass": 2
    },
    {
      "name": "Brunswick",
      "temp": 19,
      "rh": 70,
      "dewPoint": 11,
      "wind": 13,
      "gust": 20,
      "dangerClass": 2
    },
    {
      "name": "Greensville",
      "temp": 18,
      "rh": 84,
      "dewPoint": 14,
      "wind": 13,
      "gust": 21,
      "dangerClass": 2
    },
    {
      "name": "Amelia",
      "temp": 22,
      "rh": 53,
      "dewPoint": 8,
      "wind": 10,
      "gust": 21,
      "dangerClass": 2
    },
    {
      "name": "Prince George",
      "temp": 21,
      "rh": 52,
      "dewPoint": 6,
      "wind": 11,
      "gust": 26,
      "dangerClass": 2
    },
    {
      "name": "Nottoway",
      "temp": 22,
      "rh": 53,
      "dewPoint": 8,
      "wind": 10,
      "gust": 21,
      "dangerClass": 2
    }
  ],
  "alerts": [
    "Dinwiddie: High gusts (26 mph)",
    "Brunswick: High gusts (20 mph)",
    "Greensville: High gusts (21 mph)",
    "Amelia: High gusts (21 mph)",
    "Prince George: High gusts (26 mph)",
    "Nottoway: High gusts (21 mph)"
  ]
}