{
  "lastUpdated": "2025-12-19T06:28:01.102472Z",
  "counties": [
    {
      "name": "Dinwiddie",
      "temp": 58,
      "rh": 96,
      "dewPoint": 57,
      "wind": 7,
      "gust": 9,
      "dangerClass": 1
    },
    {
      "name": "Brunswick",
      "temp": 60,
      "rh": 99,
      "dewPoint": 60,
      "wind": 10,
      "gust": 13,
      "dangerClass": 1
    },
    {
      "name": "Greensville",
      "temp": 59,
      "rh": 97,
      "dewPoint": 58,
      "wind": 10,
      "gust": 13,
      "dangerClass": 1
    },
    {
      "name": "Amelia",
      "temp": 61,
      "rh": 99,
      "dewPoint": 61,
      "wind": 17,
      "gust": 23,
      "dangerClass": 2
    },
    {
      "name": "Prince George",
      "temp": 58,
      "rh": 96,
      "dewPoint": 57,
      "wind": 7,
      "gust": 9,
      "dangerClass": 1
    },
    {
      "name": "Nottoway",
      "temp": 61,
      "rh": 99,
      "dewPoint": 61,
      "wind": 17,
      "gust": 23,
      "dangerClass": 2
    }
  ],
  "alerts": [
    "Amelia: High gusts (23 mph)",
    "Nottoway: High gusts (23 mph)"
  ]
}