{
  "lastUpdated": "2026-01-14T13:06:37.080653Z",
  "counties": [
    {
      "name": "Dinwiddie",
      "temp": 37,
      "rh": 56,
      "dewPoint": 23,
      "wind": 3,
      "gust": 4,
      "dangerClass": 1
    },
    {
      "name": "Brunswick",
      "temp": 36,
      "rh": 64,
      "dewPoint": 25,
      "wind": 6,
      "gust": 8,
      "dangerClass": 1
    },
    {
      "name": "Greensville",
      "temp": 36,
      "rh": 59,
      "dewPoint": 23,
      "wind": 3,
      "gust": 4,
      "dangerClass": 1
    },
    {
      "name": "Amelia",
      "temp": 39,
      "rh": 63,
      "dewPoint": 27,
      "wind": 6,
      "gust": 8,
      "dangerClass": 1
    },
    {
      "name": "Prince George",
      "temp": 37,
      "rh": 56,
      "dewPoint": 23,
      "wind": 3,
      "gust": 4,
      "dangerClass": 1
    },
    {
      "name": "Nottoway",
      "temp": 39,
      "rh": 63,
      "dewPoint": 27,
      "wind": 6,
      "gust": 8,
      "dangerClass": 1
    }
  ],
  "alerts": []
}