{
  "lastUpdated": "2026-01-11T06:25:10.181033Z",
  "counties": [
    {
      "name": "Dinwiddie",
      "temp": 63,
      "rh": 74,
      "dewPoint": 54,
      "wind": 8,
      "gust": 10,
      "dangerClass": 1
    },
    {
      "name": "Brunswick",
      "temp": 69,
      "rh": 73,
      "dewPoint": 60,
      "wind": 8,
      "gust": 10,
      "dangerClass": 2
    },
    {
      "name": "Greensville",
      "temp": 67,
      "rh": 74,
      "dewPoint": 58,
      "wind": 8,
      "gust": 10,
      "dangerClass": 2
    },
    {
      "name": "Amelia",
      "temp": 56,
      "rh": 100,
      "dewPoint": 56,
      "wind": 3,
      "gust": 4,
      "dangerClass": 1
    },
    {
      "name": "Prince George",
      "temp": 63,
      "rh": 74,
      "dewPoint": 54,
      "wind": 8,
      "gust": 10,
      "dangerClass": 1
    },
    {
      "name": "Nottoway",
      "temp": 56,
      "rh": 100,
      "dewPoint": 56,
      "wind": 3,
      "gust": 4,
      "dangerClass": 1
    }
  ],
  "alerts": []
}